README.rst
setup.py
balancer/__init__.py
balancer/middleware.py
balancer/mixins.py
balancer/models.py
balancer/pinning.py
balancer/routers.py
django_balancer.egg-info/PKG-INFO
django_balancer.egg-info/SOURCES.txt
django_balancer.egg-info/dependency_links.txt
django_balancer.egg-info/top_level.txt