Metadata-Version: 1.1
Name: django-balancer
Version: 0.5
Summary: A set of tools for using Django's multi-db feature to balance database requests
Home-page: http://github.com/michaelhelmick/django-balancer
Author: Brandon Konkle, Mike Helmick
Author-email: mike@drund.com
License: License :: OSI Approved :: BSD License
Platform: UNKNOWN
Classifier: Framework :: Django
Classifier: Intended Audience :: Developers
Classifier: Development Status :: 3 - Alpha
